LICENSE
MANIFEST.in
README.md
setup.py
mezzanine_pageimages.egg-info/PKG-INFO
mezzanine_pageimages.egg-info/SOURCES.txt
mezzanine_pageimages.egg-info/dependency_links.txt
mezzanine_pageimages.egg-info/requires.txt
mezzanine_pageimages.egg-info/top_level.txt
pageimages/__init__.py
pageimages/admin.py
pageimages/defaults.py
pageimages/models.py
pageimages/tests.py
pageimages/views.py
pageimages/migrations/0001_initial.py
pageimages/migrations/0002_auto__add_field_pageimage_type.py
pageimages/migrations/0003_auto__add_defaultimage.py
pageimages/migrations/__init__.py
pageimages/templatetags/__init__.py
pageimages/templatetags/pageimage_tags.py