Metadata-Version: 1.0
Name: mezzanine-pageimages
Version: 0.2.1
Summary: Define (background-/banner-)images per page in mezzanine.
Home-page: http://github.com/bcs-de/mezzanine-pageimages
Author: Arnold Krille for bcs kommunikationsloesungen
Author-email: a.krille@b-c-s.de
License: Licensed under the Apache License, Version 2.0 (the "License");you may not use this file except in compliance with the License.You may obtain a copy of the License at  http://www.apache.org/licenses/LICENSE-2.0Unless required by applicable law or agreed to in writing, softwaredistributed under the License is distributed on an "AS IS" BASIS,WITHOUT WARRANTIES OR CONDITIONS OF ANY KIND, either express or implied.See the License for the specific language governing permissions andlimitation
Platform: UNKNOWN
